MOOC/__init__.py
mooc_py-0.1.0.dist-info/LICENSE
mooc_py-0.1.0.dist-info/METADATA
mooc_py-0.1.0.dist-info/WHEEL
mooc_py-0.1.0.dist-info/top_level.txt
mooc_py-0.1.0.dist-info/RECORD
