Metadata-Version: 2.1
Name: mooc-py
Version: 0.1.0
Summary: MOOC package.
Home-page: https://github.com/acheamponge/mooc_py
Author: Emmanuel Acheampong
Author-email: achampion.emma@gmail.com
License: MIT
Platform: UNKNOWN
Classifier: Programming Language :: Python
Classifier: Programming Language :: Python :: 2
Classifier: Programming Language :: Python :: 2.7
Classifier: Programming Language :: Python :: 3
Classifier: Programming Language :: Python :: 3.4
Classifier: Programming Language :: Python :: 3.5
Classifier: Programming Language :: Python :: 3.6
Classifier: Programming Language :: Python :: 3.7
